runit/Request.py
runit/__init__.py
runit/cli.py
runit/constants.py
runit/core.py
runit/exceptions.py
runit/runit.py
runit/test.py
runit/languages/__init__.py
runit/languages/javascript.py
runit/languages/multi.py
runit/languages/php.py
runit/languages/python.py
runit/languages/runtime.py
runit/modules/__init__.py
runit/modules/account.py
runit/templates/.runitignore
runit/templates/404.html
runit/templates/request.php
runit/templates/runit.json
runit/templates/javascript/main.js
runit/templates/javascript/package.json
runit/templates/javascript/runit.json
runit/templates/multi/application.py
runit/templates/multi/composer.json
runit/templates/multi/index.php
runit/templates/multi/main.js
runit/templates/multi/package.json
runit/templates/multi/request.php
runit/templates/multi/requirements.txt
runit/templates/multi/test.php
runit/templates/php/composer.json
runit/templates/php/index.php
runit/templates/php/runit.json
runit/templates/python/application.py
runit/templates/python/requirements.txt
runit/templates/python/runit.json
runit/tools/javascript/loader.js
runit/tools/javascript/runner.js
runit/tools/php/loader.php
runit/tools/php/runner.php
runit/tools/python/loader.py
runit/tools/python/runner.py
python_runit-0.3.0.dist-info/LICENSE
python_runit-0.3.0.dist-info/METADATA
python_runit-0.3.0.dist-info/WHEEL
python_runit-0.3.0.dist-info/entry_points.txt
python_runit-0.3.0.dist-info/top_level.txt
python_runit-0.3.0.dist-info/RECORD
